[
  {
    "input": "94*91+62=",
    "target": 8616
  },
  {
    "input": "56*58+32=",
    "target": 3280
  },
  {
    "input": "86*76+81=",
    "target": 6617
  },
  {
    "input": "86*7+80=",
    "target": 682
  },
  {
    "input": "82*68+94=",
    "target": 5670
  },
  {
    "input": "54*6+3=",
    "target": 327
  },
  {
    "input": "100*98+7=",
    "target": 9807
  },
  {
    "input": "54*25+92=",
    "target": 1442
  },
  {
    "input": "40*39+33=",
    "target": 1593
  },
  {
    "input": "40*84+82=",
    "target": 3442
  },
  {
    "input": "17*57+7=",
    "target": 976
  },
  {
    "input": "31*17+47=",
    "target": 574
  },
  {
    "input": "19*3+35=",
    "target": 92
  },
  {
    "input": "9*93+74=",
    "target": 911
  },
  {
    "input": "50*92+70=",
    "target": 4670
  },
  {
    "input": "47*43+62=",
    "target": 2083
  },
  {
    "input": "65*4+12=",
    "target": 272
  },
  {
    "input": "24*34+92=",
    "target": 908
  },
  {
    "input": "60*1+51=",
    "target": 111
  },
  {
    "input": "38*58+19=",
    "target": 2223
  },
  {
    "input": "27*75+39=",
    "target": 2064
  },
  {
    "input": "45*40+47=",
    "target": 1847
  },
  {
    "input": "80*38+21=",
    "target": 3061
  },
  {
    "input": "89*78+100=",
    "target": 7042
  },
  {
    "input": "24*34+80=",
    "target": 896
  },
  {
    "input": "72*23+8=",
    "target": 1664
  },
  {
    "input": "38*85+38=",
    "target": 3268
  },
  {
    "input": "85*27+82=",
    "target": 2377
  },
  {
    "input": "18*20+61=",
    "target": 421
  },
  {
    "input": "64*43+65=",
    "target": 2817
  },
  {
    "input": "20*59+57=",
    "target": 1237
  },
  {
    "input": "20*49+8=",
    "target": 988
  },
  {
    "input": "70*23+3=",
    "target": 1613
  },
  {
    "input": "51*59+6=",
    "target": 3015
  },
  {
    "input": "40*28+34=",
    "target": 1154
  },
  {
    "input": "42*10+50=",
    "target": 470
  },
  {
    "input": "66*81+9=",
    "target": 5355
  },
  {
    "input": "7*48+6=",
    "target": 342
  },
  {
    "input": "57*62+2=",
    "target": 3536
  },
  {
    "input": "95*80+17=",
    "target": 7617
  },
  {
    "input": "52*78+16=",
    "target": 4072
  },
  {
    "input": "69*78+66=",
    "target": 5448
  },
  {
    "input": "65*55+57=",
    "target": 3632
  },
  {
    "input": "29*77+34=",
    "target": 2267
  },
  {
    "input": "71*95+52=",
    "target": 6797
  },
  {
    "input": "18*51+63=",
    "target": 981
  },
  {
    "input": "18*46+77=",
    "target": 905
  },
  {
    "input": "96*69+26=",
    "target": 6650
  },
  {
    "input": "55*54+68=",
    "target": 3038
  },
  {
    "input": "3*22+25=",
    "target": 91
  },
  {
    "input": "88*53+80=",
    "target": 4744
  },
  {
    "input": "55*7+97=",
    "target": 482
  },
  {
    "input": "70*34+42=",
    "target": 2422
  },
  {
    "input": "5*23+1=",
    "target": 116
  },
  {
    "input": "23*77+1=",
    "target": 1772
  },
  {
    "input": "29*89+15=",
    "target": 2596
  },
  {
    "input": "23*37+4=",
    "target": 855
  },
  {
    "input": "100*85+3=",
    "target": 8503
  },
  {
    "input": "6*26+21=",
    "target": 177
  },
  {
    "input": "33*67+9=",
    "target": 2220
  },
  {
    "input": "57*12+15=",
    "target": 699
  },
  {
    "input": "68*60+90=",
    "target": 4170
  },
  {
    "input": "65*50+47=",
    "target": 3297
  },
  {
    "input": "70*24+59=",
    "target": 1739
  },
  {
    "input": "94*10+34=",
    "target": 974
  },
  {
    "input": "69*2+17=",
    "target": 155
  },
  {
    "input": "3*85+96=",
    "target": 351
  },
  {
    "input": "87*94+90=",
    "target": 8268
  },
  {
    "input": "2*92+70=",
    "target": 254
  },
  {
    "input": "30*10+56=",
    "target": 356
  },
  {
    "input": "52*17+85=",
    "target": 969
  },
  {
    "input": "13*19+35=",
    "target": 282
  },
  {
    "input": "97*26+26=",
    "target": 2548
  },
  {
    "input": "60*1+5=",
    "target": 65
  },
  {
    "input": "68*9+67=",
    "target": 679
  },
  {
    "input": "55*69+76=",
    "target": 3871
  },
  {
    "input": "4*29+26=",
    "target": 142
  },
  {
    "input": "87*60+75=",
    "target": 5295
  },
  {
    "input": "41*85+94=",
    "target": 3579
  },
  {
    "input": "60*84+89=",
    "target": 5129
  },
  {
    "input": "99*79+19=",
    "target": 7840
  },
  {
    "input": "62*74+66=",
    "target": 4654
  },
  {
    "input": "44*18+93=",
    "target": 885
  },
  {
    "input": "36*95+55=",
    "target": 3475
  },
  {
    "input": "47*11+62=",
    "target": 579
  },
  {
    "input": "49*77+28=",
    "target": 3801
  },
  {
    "input": "1*81+68=",
    "target": 149
  },
  {
    "input": "56*49+25=",
    "target": 2769
  },
  {
    "input": "42*45+96=",
    "target": 1986
  },
  {
    "input": "16*39+34=",
    "target": 658
  },
  {
    "input": "69*54+18=",
    "target": 3744
  },
  {
    "input": "72*76+53=",
    "target": 5525
  },
  {
    "input": "83*2+46=",
    "target": 212
  },
  {
    "input": "68*13+44=",
    "target": 928
  },
  {
    "input": "28*91+100=",
    "target": 2648
  },
  {
    "input": "21*27+90=",
    "target": 657
  },
  {
    "input": "46*98+9=",
    "target": 4517
  },
  {
    "input": "48*50+41=",
    "target": 2441
  },
  {
    "input": "2*65+11=",
    "target": 141
  },
  {
    "input": "97*66+52=",
    "target": 6454
  },
  {
    "input": "13*96+20=",
    "target": 1268
  },
  {
    "input": "54*59+6=",
    "target": 3192
  },
  {
    "input": "84*83+95=",
    "target": 7067
  },
  {
    "input": "13*2+67=",
    "target": 93
  },
  {
    "input": "74*80+5=",
    "target": 5925
  },
  {
    "input": "19*63+62=",
    "target": 1259
  },
  {
    "input": "43*54+14=",
    "target": 2336
  },
  {
    "input": "85*37+35=",
    "target": 3180
  },
  {
    "input": "23*70+62=",
    "target": 1672
  },
  {
    "input": "3*13+22=",
    "target": 61
  },
  {
    "input": "84*96+77=",
    "target": 8141
  },
  {
    "input": "32*3+7=",
    "target": 103
  },
  {
    "input": "6*15+15=",
    "target": 105
  },
  {
    "input": "97*55+50=",
    "target": 5385
  },
  {
    "input": "17*40+72=",
    "target": 752
  },
  {
    "input": "67*93+46=",
    "target": 6277
  },
  {
    "input": "1*87+96=",
    "target": 183
  },
  {
    "input": "94*66+52=",
    "target": 6256
  },
  {
    "input": "79*20+17=",
    "target": 1597
  },
  {
    "input": "62*37+96=",
    "target": 2390
  },
  {
    "input": "32*96+60=",
    "target": 3132
  },
  {
    "input": "96*13+3=",
    "target": 1251
  },
  {
    "input": "92*77+32=",
    "target": 7116
  },
  {
    "input": "63*29+100=",
    "target": 1927
  },
  {
    "input": "56*92+61=",
    "target": 5213
  },
  {
    "input": "74*16+50=",
    "target": 1234
  },
  {
    "input": "8*34+18=",
    "target": 290
  },
  {
    "input": "12*18+64=",
    "target": 280
  },
  {
    "input": "65*50+97=",
    "target": 3347
  },
  {
    "input": "31*2+59=",
    "target": 121
  },
  {
    "input": "58*23+94=",
    "target": 1428
  },
  {
    "input": "18*57+99=",
    "target": 1125
  },
  {
    "input": "66*58+60=",
    "target": 3888
  },
  {
    "input": "21*32+65=",
    "target": 737
  },
  {
    "input": "48*5+5=",
    "target": 245
  },
  {
    "input": "12*2+25=",
    "target": 49
  },
  {
    "input": "10*78+52=",
    "target": 832
  },
  {
    "input": "99*28+31=",
    "target": 2803
  },
  {
    "input": "18*87+54=",
    "target": 1620
  },
  {
    "input": "67*20+45=",
    "target": 1385
  },
  {
    "input": "91*19+87=",
    "target": 1816
  },
  {
    "input": "96*60+19=",
    "target": 5779
  },
  {
    "input": "33*83+61=",
    "target": 2800
  },
  {
    "input": "46*25+49=",
    "target": 1199
  },
  {
    "input": "29*14+53=",
    "target": 459
  },
  {
    "input": "49*49+76=",
    "target": 2477
  },
  {
    "input": "38*29+83=",
    "target": 1185
  },
  {
    "input": "98*9+76=",
    "target": 958
  },
  {
    "input": "4*54+28=",
    "target": 244
  },
  {
    "input": "85*47+9=",
    "target": 4004
  },
  {
    "input": "21*49+56=",
    "target": 1085
  },
  {
    "input": "7*34+28=",
    "target": 266
  },
  {
    "input": "15*2+21=",
    "target": 51
  },
  {
    "input": "87*73+78=",
    "target": 6429
  },
  {
    "input": "77*69+55=",
    "target": 5368
  },
  {
    "input": "5*43+50=",
    "target": 265
  },
  {
    "input": "31*42+9=",
    "target": 1311
  },
  {
    "input": "11*69+98=",
    "target": 857
  },
  {
    "input": "22*1+29=",
    "target": 51
  },
  {
    "input": "49*54+22=",
    "target": 2668
  },
  {
    "input": "43*53+74=",
    "target": 2353
  },
  {
    "input": "44*89+31=",
    "target": 3947
  },
  {
    "input": "96*58+78=",
    "target": 5646
  },
  {
    "input": "87*59+90=",
    "target": 5223
  },
  {
    "input": "51*71+15=",
    "target": 3636
  },
  {
    "input": "50*29+17=",
    "target": 1467
  },
  {
    "input": "69*61+90=",
    "target": 4299
  },
  {
    "input": "36*18+5=",
    "target": 653
  },
  {
    "input": "18*44+11=",
    "target": 803
  },
  {
    "input": "23*41+5=",
    "target": 948
  },
  {
    "input": "86*65+91=",
    "target": 5681
  },
  {
    "input": "83*17+61=",
    "target": 1472
  },
  {
    "input": "89*12+35=",
    "target": 1103
  },
  {
    "input": "26*75+11=",
    "target": 1961
  },
  {
    "input": "71*52+38=",
    "target": 3730
  },
  {
    "input": "43*9+45=",
    "target": 432
  },
  {
    "input": "52*70+61=",
    "target": 3701
  },
  {
    "input": "98*16+53=",
    "target": 1621
  },
  {
    "input": "60*62+79=",
    "target": 3799
  },
  {
    "input": "30*55+99=",
    "target": 1749
  },
  {
    "input": "41*76+69=",
    "target": 3185
  },
  {
    "input": "10*86+82=",
    "target": 942
  },
  {
    "input": "12*31+25=",
    "target": 397
  },
  {
    "input": "65*90+3=",
    "target": 5853
  },
  {
    "input": "35*95+3=",
    "target": 3328
  },
  {
    "input": "87*54+83=",
    "target": 4781
  },
  {
    "input": "10*58+18=",
    "target": 598
  },
  {
    "input": "9*89+62=",
    "target": 863
  },
  {
    "input": "86*72+66=",
    "target": 6258
  },
  {
    "input": "85*11+19=",
    "target": 954
  },
  {
    "input": "26*69+3=",
    "target": 1797
  },
  {
    "input": "26*14+100=",
    "target": 464
  },
  {
    "input": "98*40+45=",
    "target": 3965
  },
  {
    "input": "34*75+71=",
    "target": 2621
  },
  {
    "input": "41*41+67=",
    "target": 1748
  },
  {
    "input": "91*25+13=",
    "target": 2288
  },
  {
    "input": "96*34+50=",
    "target": 3314
  },
  {
    "input": "35*53+47=",
    "target": 1902
  },
  {
    "input": "2*23+40=",
    "target": 86
  },
  {
    "input": "53*79+29=",
    "target": 4216
  },
  {
    "input": "73*1+45=",
    "target": 118
  },
  {
    "input": "90*59+15=",
    "target": 5325
  },
  {
    "input": "7*54+90=",
    "target": 468
  },
  {
    "input": "39*3+73=",
    "target": 190
  },
  {
    "input": "78*87+100=",
    "target": 6886
  },
  {
    "input": "58*74+86=",
    "target": 4378
  },
  {
    "input": "33*4+11=",
    "target": 143
  },
  {
    "input": "15*51+46=",
    "target": 811
  },
  {
    "input": "77*99+75=",
    "target": 7698
  },
  {
    "input": "84*1+63=",
    "target": 147
  },
  {
    "input": "67*62+57=",
    "target": 4211
  },
  {
    "input": "73*13+56=",
    "target": 1005
  },
  {
    "input": "39*94+35=",
    "target": 3701
  },
  {
    "input": "80*79+25=",
    "target": 6345
  },
  {
    "input": "63*33+24=",
    "target": 2103
  },
  {
    "input": "96*39+55=",
    "target": 3799
  },
  {
    "input": "68*60+44=",
    "target": 4124
  },
  {
    "input": "13*2+80=",
    "target": 106
  },
  {
    "input": "85*41+76=",
    "target": 3561
  },
  {
    "input": "99*87+56=",
    "target": 8669
  },
  {
    "input": "92*5+75=",
    "target": 535
  },
  {
    "input": "57*34+78=",
    "target": 2016
  },
  {
    "input": "43*48+90=",
    "target": 2154
  },
  {
    "input": "76*40+76=",
    "target": 3116
  },
  {
    "input": "93*2+81=",
    "target": 267
  },
  {
    "input": "74*43+47=",
    "target": 3229
  },
  {
    "input": "69*24+89=",
    "target": 1745
  },
  {
    "input": "1*40+17=",
    "target": 57
  },
  {
    "input": "59*61+28=",
    "target": 3627
  },
  {
    "input": "78*40+75=",
    "target": 3195
  },
  {
    "input": "36*62+66=",
    "target": 2298
  },
  {
    "input": "64*3+46=",
    "target": 238
  },
  {
    "input": "18*22+43=",
    "target": 439
  },
  {
    "input": "57*51+25=",
    "target": 2932
  },
  {
    "input": "73*1+97=",
    "target": 170
  },
  {
    "input": "43*78+1=",
    "target": 3355
  },
  {
    "input": "2*86+53=",
    "target": 225
  },
  {
    "input": "60*48+90=",
    "target": 2970
  },
  {
    "input": "73*44+19=",
    "target": 3231
  },
  {
    "input": "9*74+22=",
    "target": 688
  },
  {
    "input": "57*10+87=",
    "target": 657
  },
  {
    "input": "34*82+58=",
    "target": 2846
  },
  {
    "input": "59*29+35=",
    "target": 1746
  },
  {
    "input": "22*47+67=",
    "target": 1101
  },
  {
    "input": "8*51+65=",
    "target": 473
  },
  {
    "input": "98*13+33=",
    "target": 1307
  },
  {
    "input": "40*84+63=",
    "target": 3423
  },
  {
    "input": "38*68+82=",
    "target": 2666
  },
  {
    "input": "99*11+66=",
    "target": 1155
  },
  {
    "input": "16*5+21=",
    "target": 101
  },
  {
    "input": "9*39+20=",
    "target": 371
  },
  {
    "input": "51*53+71=",
    "target": 2774
  },
  {
    "input": "95*60+7=",
    "target": 5707
  },
  {
    "input": "58*99+3=",
    "target": 5745
  },
  {
    "input": "68*87+61=",
    "target": 5977
  },
  {
    "input": "10*30+44=",
    "target": 344
  },
  {
    "input": "71*8+25=",
    "target": 593
  },
  {
    "input": "82*80+10=",
    "target": 6570
  },
  {
    "input": "90*46+72=",
    "target": 4212
  },
  {
    "input": "82*33+15=",
    "target": 2721
  },
  {
    "input": "54*67+97=",
    "target": 3715
  },
  {
    "input": "52*57+60=",
    "target": 3024
  },
  {
    "input": "90*30+67=",
    "target": 2767
  },
  {
    "input": "8*69+7=",
    "target": 559
  },
  {
    "input": "48*18+49=",
    "target": 913
  },
  {
    "input": "46*24+40=",
    "target": 1144
  },
  {
    "input": "51*67+5=",
    "target": 3422
  },
  {
    "input": "84*57+46=",
    "target": 4834
  },
  {
    "input": "70*83+95=",
    "target": 5905
  },
  {
    "input": "22*86+54=",
    "target": 1946
  },
  {
    "input": "66*33+67=",
    "target": 2245
  },
  {
    "input": "14*51+100=",
    "target": 814
  },
  {
    "input": "51*53+18=",
    "target": 2721
  },
  {
    "input": "86*9+63=",
    "target": 837
  },
  {
    "input": "55*97+60=",
    "target": 5395
  },
  {
    "input": "11*60+29=",
    "target": 689
  },
  {
    "input": "28*70+28=",
    "target": 1988
  },
  {
    "input": "45*70+99=",
    "target": 3249
  },
  {
    "input": "28*25+49=",
    "target": 749
  },
  {
    "input": "88*52+27=",
    "target": 4603
  },
  {
    "input": "54*42+73=",
    "target": 2341
  },
  {
    "input": "41*42+46=",
    "target": 1768
  },
  {
    "input": "47*27+48=",
    "target": 1317
  },
  {
    "input": "69*19+46=",
    "target": 1357
  },
  {
    "input": "1*19+38=",
    "target": 57
  },
  {
    "input": "96*82+9=",
    "target": 7881
  },
  {
    "input": "49*99+62=",
    "target": 4913
  },
  {
    "input": "74*25+100=",
    "target": 1950
  },
  {
    "input": "86*14+82=",
    "target": 1286
  },
  {
    "input": "83*99+78=",
    "target": 8295
  },
  {
    "input": "91*81+71=",
    "target": 7442
  },
  {
    "input": "91*19+26=",
    "target": 1755
  },
  {
    "input": "47*80+22=",
    "target": 3782
  },
  {
    "input": "10*76+33=",
    "target": 793
  },
  {
    "input": "12*69+13=",
    "target": 841
  },
  {
    "input": "47*74+93=",
    "target": 3571
  },
  {
    "input": "62*10+25=",
    "target": 645
  },
  {
    "input": "52*7+12=",
    "target": 376
  },
  {
    "input": "83*22+100=",
    "target": 1926
  },
  {
    "input": "64*100+52=",
    "target": 6452
  },
  {
    "input": "75*54+50=",
    "target": 4100
  },
  {
    "input": "79*20+6=",
    "target": 1586
  },
  {
    "input": "86*4+54=",
    "target": 398
  },
  {
    "input": "16*33+90=",
    "target": 618
  },
  {
    "input": "42*67+15=",
    "target": 2829
  },
  {
    "input": "70*82+100=",
    "target": 5840
  },
  {
    "input": "70*87+97=",
    "target": 6187
  },
  {
    "input": "100*68+48=",
    "target": 6848
  },
  {
    "input": "61*88+71=",
    "target": 5439
  },
  {
    "input": "7*39+88=",
    "target": 361
  },
  {
    "input": "44*79+32=",
    "target": 3508
  },
  {
    "input": "92*34+23=",
    "target": 3151
  },
  {
    "input": "61*89+50=",
    "target": 5479
  },
  {
    "input": "11*9+11=",
    "target": 110
  },
  {
    "input": "32*13+56=",
    "target": 472
  },
  {
    "input": "86*100+45=",
    "target": 8645
  },
  {
    "input": "44*16+61=",
    "target": 765
  },
  {
    "input": "97*94+5=",
    "target": 9123
  },
  {
    "input": "37*95+16=",
    "target": 3531
  },
  {
    "input": "53*59+52=",
    "target": 3179
  },
  {
    "input": "53*15+51=",
    "target": 846
  },
  {
    "input": "58*50+48=",
    "target": 2948
  },
  {
    "input": "22*54+28=",
    "target": 1216
  },
  {
    "input": "75*15+87=",
    "target": 1212
  },
  {
    "input": "54*84+7=",
    "target": 4543
  },
  {
    "input": "5*53+74=",
    "target": 339
  },
  {
    "input": "44*62+86=",
    "target": 2814
  },
  {
    "input": "4*48+93=",
    "target": 285
  },
  {
    "input": "89*1+71=",
    "target": 160
  },
  {
    "input": "58*98+4=",
    "target": 5688
  },
  {
    "input": "74*3+93=",
    "target": 315
  },
  {
    "input": "79*59+94=",
    "target": 4755
  },
  {
    "input": "46*18+33=",
    "target": 861
  },
  {
    "input": "11*87+33=",
    "target": 990
  },
  {
    "input": "99*100+97=",
    "target": 9997
  },
  {
    "input": "13*18+22=",
    "target": 256
  },
  {
    "input": "34*75+75=",
    "target": 2625
  },
  {
    "input": "41*36+33=",
    "target": 1509
  },
  {
    "input": "40*93+49=",
    "target": 3769
  },
  {
    "input": "84*39+21=",
    "target": 3297
  },
  {
    "input": "42*89+27=",
    "target": 3765
  },
  {
    "input": "65*88+54=",
    "target": 5774
  },
  {
    "input": "64*19+74=",
    "target": 1290
  },
  {
    "input": "44*66+45=",
    "target": 2949
  },
  {
    "input": "77*30+22=",
    "target": 2332
  },
  {
    "input": "21*27+14=",
    "target": 581
  },
  {
    "input": "86*96+78=",
    "target": 8334
  },
  {
    "input": "54*51+73=",
    "target": 2827
  },
  {
    "input": "95*45+43=",
    "target": 4318
  },
  {
    "input": "11*42+12=",
    "target": 474
  },
  {
    "input": "2*40+20=",
    "target": 100
  },
  {
    "input": "43*23+18=",
    "target": 1007
  },
  {
    "input": "3*38+71=",
    "target": 185
  },
  {
    "input": "2*95+31=",
    "target": 221
  },
  {
    "input": "17*18+3=",
    "target": 309
  },
  {
    "input": "16*90+82=",
    "target": 1522
  },
  {
    "input": "1*89+49=",
    "target": 138
  },
  {
    "input": "29*12+83=",
    "target": 431
  },
  {
    "input": "56*33+35=",
    "target": 1883
  },
  {
    "input": "84*37+56=",
    "target": 3164
  },
  {
    "input": "100*17+12=",
    "target": 1712
  },
  {
    "input": "28*8+36=",
    "target": 260
  },
  {
    "input": "7*83+11=",
    "target": 592
  },
  {
    "input": "89*53+20=",
    "target": 4737
  },
  {
    "input": "42*93+10=",
    "target": 3916
  },
  {
    "input": "50*2+25=",
    "target": 125
  },
  {
    "input": "98*76+90=",
    "target": 7538
  },
  {
    "input": "80*18+9=",
    "target": 1449
  },
  {
    "input": "6*6+86=",
    "target": 122
  },
  {
    "input": "30*20+45=",
    "target": 645
  },
  {
    "input": "99*43+60=",
    "target": 4317
  },
  {
    "input": "53*26+32=",
    "target": 1410
  },
  {
    "input": "80*68+92=",
    "target": 5532
  },
  {
    "input": "15*98+15=",
    "target": 1485
  },
  {
    "input": "20*75+55=",
    "target": 1555
  },
  {
    "input": "41*14+38=",
    "target": 612
  },
  {
    "input": "95*21+35=",
    "target": 2030
  },
  {
    "input": "57*33+66=",
    "target": 1947
  },
  {
    "input": "54*23+65=",
    "target": 1307
  },
  {
    "input": "96*15+42=",
    "target": 1482
  },
  {
    "input": "57*74+21=",
    "target": 4239
  },
  {
    "input": "2*29+94=",
    "target": 152
  },
  {
    "input": "85*68+68=",
    "target": 5848
  },
  {
    "input": "99*59+13=",
    "target": 5854
  },
  {
    "input": "59*69+55=",
    "target": 4126
  },
  {
    "input": "2*37+73=",
    "target": 147
  },
  {
    "input": "77*22+25=",
    "target": 1719
  },
  {
    "input": "97*46+70=",
    "target": 4532
  },
  {
    "input": "20*99+62=",
    "target": 2042
  },
  {
    "input": "11*31+90=",
    "target": 431
  },
  {
    "input": "65*52+56=",
    "target": 3436
  },
  {
    "input": "1*91+69=",
    "target": 160
  },
  {
    "input": "89*87+21=",
    "target": 7764
  },
  {
    "input": "28*62+70=",
    "target": 1806
  },
  {
    "input": "23*75+17=",
    "target": 1742
  },
  {
    "input": "87*28+85=",
    "target": 2521
  },
  {
    "input": "69*45+57=",
    "target": 3162
  },
  {
    "input": "90*34+92=",
    "target": 3152
  },
  {
    "input": "13*31+93=",
    "target": 496
  },
  {
    "input": "75*37+96=",
    "target": 2871
  },
  {
    "input": "28*10+83=",
    "target": 363
  },
  {
    "input": "27*23+59=",
    "target": 680
  },
  {
    "input": "65*18+48=",
    "target": 1218
  },
  {
    "input": "21*22+12=",
    "target": 474
  },
  {
    "input": "40*88+39=",
    "target": 3559
  },
  {
    "input": "21*78+51=",
    "target": 1689
  },
  {
    "input": "12*12+65=",
    "target": 209
  },
  {
    "input": "42*63+1=",
    "target": 2647
  },
  {
    "input": "48*90+89=",
    "target": 4409
  },
  {
    "input": "66*42+59=",
    "target": 2831
  },
  {
    "input": "91*23+40=",
    "target": 2133
  },
  {
    "input": "54*84+71=",
    "target": 4607
  },
  {
    "input": "12*12+4=",
    "target": 148
  },
  {
    "input": "95*88+19=",
    "target": 8379
  },
  {
    "input": "37*34+9=",
    "target": 1267
  },
  {
    "input": "88*83+81=",
    "target": 7385
  },
  {
    "input": "48*51+30=",
    "target": 2478
  },
  {
    "input": "69*95+75=",
    "target": 6630
  },
  {
    "input": "26*74+21=",
    "target": 1945
  },
  {
    "input": "56*96+64=",
    "target": 5440
  },
  {
    "input": "34*78+2=",
    "target": 2654
  },
  {
    "input": "88*27+39=",
    "target": 2415
  },
  {
    "input": "17*38+71=",
    "target": 717
  },
  {
    "input": "18*6+65=",
    "target": 173
  },
  {
    "input": "9*97+65=",
    "target": 938
  },
  {
    "input": "74*79+31=",
    "target": 5877
  },
  {
    "input": "99*68+90=",
    "target": 6822
  },
  {
    "input": "65*50+35=",
    "target": 3285
  },
  {
    "input": "14*75+41=",
    "target": 1091
  },
  {
    "input": "51*94+73=",
    "target": 4867
  },
  {
    "input": "85*83+77=",
    "target": 7132
  },
  {
    "input": "23*24+26=",
    "target": 578
  },
  {
    "input": "99*55+36=",
    "target": 5481
  },
  {
    "input": "63*52+41=",
    "target": 3317
  },
  {
    "input": "33*68+8=",
    "target": 2252
  },
  {
    "input": "47*63+15=",
    "target": 2976
  },
  {
    "input": "57*87+50=",
    "target": 5009
  },
  {
    "input": "1*14+25=",
    "target": 39
  },
  {
    "input": "67*80+54=",
    "target": 5414
  },
  {
    "input": "88*1+87=",
    "target": 175
  },
  {
    "input": "5*49+94=",
    "target": 339
  },
  {
    "input": "64*8+50=",
    "target": 562
  },
  {
    "input": "13*42+87=",
    "target": 633
  },
  {
    "input": "23*58+48=",
    "target": 1382
  },
  {
    "input": "60*78+25=",
    "target": 4705
  },
  {
    "input": "57*17+23=",
    "target": 992
  },
  {
    "input": "28*74+11=",
    "target": 2083
  },
  {
    "input": "73*55+54=",
    "target": 4069
  },
  {
    "input": "55*71+20=",
    "target": 3925
  },
  {
    "input": "9*16+31=",
    "target": 175
  },
  {
    "input": "58*17+88=",
    "target": 1074
  },
  {
    "input": "61*98+25=",
    "target": 6003
  },
  {
    "input": "57*52+41=",
    "target": 3005
  },
  {
    "input": "34*90+87=",
    "target": 3147
  },
  {
    "input": "56*81+100=",
    "target": 4636
  },
  {
    "input": "96*62+59=",
    "target": 6011
  },
  {
    "input": "38*91+44=",
    "target": 3502
  },
  {
    "input": "75*40+71=",
    "target": 3071
  },
  {
    "input": "84*14+39=",
    "target": 1215
  },
  {
    "input": "67*80+57=",
    "target": 5417
  },
  {
    "input": "36*38+56=",
    "target": 1424
  },
  {
    "input": "97*16+96=",
    "target": 1648
  },
  {
    "input": "17*53+71=",
    "target": 972
  },
  {
    "input": "42*12+4=",
    "target": 508
  },
  {
    "input": "25*100+20=",
    "target": 2520
  },
  {
    "input": "36*56+42=",
    "target": 2058
  },
  {
    "input": "77*54+85=",
    "target": 4243
  },
  {
    "input": "53*99+15=",
    "target": 5262
  },
  {
    "input": "43*54+7=",
    "target": 2329
  },
  {
    "input": "62*9+93=",
    "target": 651
  },
  {
    "input": "7*87+2=",
    "target": 611
  },
  {
    "input": "46*27+99=",
    "target": 1341
  },
  {
    "input": "47*48+53=",
    "target": 2309
  },
  {
    "input": "68*49+37=",
    "target": 3369
  },
  {
    "input": "99*100+47=",
    "target": 9947
  },
  {
    "input": "92*10+63=",
    "target": 983
  },
  {
    "input": "76*25+7=",
    "target": 1907
  },
  {
    "input": "56*72+34=",
    "target": 4066
  },
  {
    "input": "7*36+27=",
    "target": 279
  },
  {
    "input": "83*29+4=",
    "target": 2411
  },
  {
    "input": "89*59+25=",
    "target": 5276
  },
  {
    "input": "44*9+41=",
    "target": 437
  },
  {
    "input": "74*82+46=",
    "target": 6114
  },
  {
    "input": "29*3+6=",
    "target": 93
  },
  {
    "input": "9*90+39=",
    "target": 849
  },
  {
    "input": "65*44+51=",
    "target": 2911
  },
  {
    "input": "6*55+62=",
    "target": 392
  },
  {
    "input": "65*34+81=",
    "target": 2291
  },
  {
    "input": "48*94+42=",
    "target": 4554
  },
  {
    "input": "62*67+85=",
    "target": 4239
  },
  {
    "input": "31*88+17=",
    "target": 2745
  },
  {
    "input": "18*25+25=",
    "target": 475
  },
  {
    "input": "85*12+99=",
    "target": 1119
  },
  {
    "input": "82*73+92=",
    "target": 6078
  },
  {
    "input": "13*71+19=",
    "target": 942
  },
  {
    "input": "37*52+9=",
    "target": 1933
  },
  {
    "input": "93*44+79=",
    "target": 4171
  },
  {
    "input": "71*93+74=",
    "target": 6677
  },
  {
    "input": "70*64+2=",
    "target": 4482
  },
  {
    "input": "59*40+2=",
    "target": 2362
  },
  {
    "input": "39*66+69=",
    "target": 2643
  },
  {
    "input": "82*70+17=",
    "target": 5757
  },
  {
    "input": "59*52+43=",
    "target": 3111
  },
  {
    "input": "58*73+5=",
    "target": 4239
  },
  {
    "input": "33*32+19=",
    "target": 1075
  },
  {
    "input": "3*48+52=",
    "target": 196
  },
  {
    "input": "8*38+79=",
    "target": 383
  },
  {
    "input": "45*77+14=",
    "target": 3479
  },
  {
    "input": "13*7+64=",
    "target": 155
  },
  {
    "input": "6*52+58=",
    "target": 370
  },
  {
    "input": "27*26+17=",
    "target": 719
  },
  {
    "input": "30*38+81=",
    "target": 1221
  },
  {
    "input": "39*94+82=",
    "target": 3748
  },
  {
    "input": "63*11+86=",
    "target": 779
  },
  {
    "input": "37*96+30=",
    "target": 3582
  },
  {
    "input": "34*67+76=",
    "target": 2354
  },
  {
    "input": "59*64+100=",
    "target": 3876
  },
  {
    "input": "72*81+38=",
    "target": 5870
  },
  {
    "input": "46*90+81=",
    "target": 4221
  },
  {
    "input": "20*90+59=",
    "target": 1859
  },
  {
    "input": "30*77+85=",
    "target": 2395
  },
  {
    "input": "8*55+42=",
    "target": 482
  },
  {
    "input": "30*76+5=",
    "target": 2285
  },
  {
    "input": "49*52+32=",
    "target": 2580
  },
  {
    "input": "50*87+68=",
    "target": 4418
  },
  {
    "input": "29*10+2=",
    "target": 292
  },
  {
    "input": "9*44+3=",
    "target": 399
  },
  {
    "input": "86*65+94=",
    "target": 5684
  },
  {
    "input": "2*25+16=",
    "target": 66
  },
  {
    "input": "15*56+18=",
    "target": 858
  },
  {
    "input": "95*60+6=",
    "target": 5706
  },
  {
    "input": "25*13+23=",
    "target": 348
  },
  {
    "input": "34*47+99=",
    "target": 1697
  },
  {
    "input": "4*48+99=",
    "target": 291
  },
  {
    "input": "9*12+30=",
    "target": 138
  },
  {
    "input": "42*2+20=",
    "target": 104
  },
  {
    "input": "73*7+80=",
    "target": 591
  },
  {
    "input": "60*98+63=",
    "target": 5943
  },
  {
    "input": "56*66+13=",
    "target": 3709
  },
  {
    "input": "77*45+20=",
    "target": 3485
  },
  {
    "input": "58*84+72=",
    "target": 4944
  },
  {
    "input": "5*54+68=",
    "target": 338
  },
  {
    "input": "9*44+16=",
    "target": 412
  },
  {
    "input": "68*63+41=",
    "target": 4325
  },
  {
    "input": "86*62+73=",
    "target": 5405
  },
  {
    "input": "7*69+28=",
    "target": 511
  },
  {
    "input": "32*87+28=",
    "target": 2812
  },
  {
    "input": "40*48+91=",
    "target": 2011
  },
  {
    "input": "6*83+88=",
    "target": 586
  },
  {
    "input": "49*64+75=",
    "target": 3211
  },
  {
    "input": "9*55+67=",
    "target": 562
  },
  {
    "input": "15*37+77=",
    "target": 632
  },
  {
    "input": "55*29+70=",
    "target": 1665
  },
  {
    "input": "99*51+99=",
    "target": 5148
  },
  {
    "input": "96*48+19=",
    "target": 4627
  },
  {
    "input": "6*66+64=",
    "target": 460
  },
  {
    "input": "92*94+14=",
    "target": 8662
  },
  {
    "input": "60*42+78=",
    "target": 2598
  },
  {
    "input": "10*58+15=",
    "target": 595
  },
  {
    "input": "42*7+74=",
    "target": 368
  },
  {
    "input": "98*74+12=",
    "target": 7264
  },
  {
    "input": "31*23+47=",
    "target": 760
  },
  {
    "input": "22*43+21=",
    "target": 967
  },
  {
    "input": "77*55+100=",
    "target": 4335
  },
  {
    "input": "92*47+91=",
    "target": 4415
  },
  {
    "input": "98*38+23=",
    "target": 3747
  },
  {
    "input": "28*30+96=",
    "target": 936
  },
  {
    "input": "49*98+78=",
    "target": 4880
  },
  {
    "input": "89*74+1=",
    "target": 6587
  },
  {
    "input": "57*8+98=",
    "target": 554
  },
  {
    "input": "55*8+64=",
    "target": 504
  },
  {
    "input": "25*10+29=",
    "target": 279
  },
  {
    "input": "72*25+32=",
    "target": 1832
  },
  {
    "input": "44*40+15=",
    "target": 1775
  },
  {
    "input": "43*35+69=",
    "target": 1574
  },
  {
    "input": "81*5+4=",
    "target": 409
  },
  {
    "input": "34*93+2=",
    "target": 3164
  },
  {
    "input": "57*34+32=",
    "target": 1970
  },
  {
    "input": "17*88+44=",
    "target": 1540
  },
  {
    "input": "70*92+61=",
    "target": 6501
  },
  {
    "input": "7*33+31=",
    "target": 262
  },
  {
    "input": "53*4+72=",
    "target": 284
  },
  {
    "input": "69*12+28=",
    "target": 856
  },
  {
    "input": "90*87+79=",
    "target": 7909
  },
  {
    "input": "95*32+52=",
    "target": 3092
  },
  {
    "input": "73*89+12=",
    "target": 6509
  },
  {
    "input": "82*26+72=",
    "target": 2204
  },
  {
    "input": "33*97+63=",
    "target": 3264
  },
  {
    "input": "73*18+38=",
    "target": 1352
  },
  {
    "input": "2*31+9=",
    "target": 71
  },
  {
    "input": "32*16+5=",
    "target": 517
  },
  {
    "input": "33*75+43=",
    "target": 2518
  },
  {
    "input": "81*50+48=",
    "target": 4098
  },
  {
    "input": "62*22+86=",
    "target": 1450
  },
  {
    "input": "90*61+70=",
    "target": 5560
  },
  {
    "input": "65*10+72=",
    "target": 722
  },
  {
    "input": "4*44+88=",
    "target": 264
  },
  {
    "input": "96*68+76=",
    "target": 6604
  },
  {
    "input": "46*21+41=",
    "target": 1007
  },
  {
    "input": "40*91+23=",
    "target": 3663
  },
  {
    "input": "56*97+51=",
    "target": 5483
  },
  {
    "input": "58*53+64=",
    "target": 3138
  },
  {
    "input": "66*12+32=",
    "target": 824
  },
  {
    "input": "92*77+30=",
    "target": 7114
  },
  {
    "input": "84*82+92=",
    "target": 6980
  },
  {
    "input": "4*24+1=",
    "target": 97
  },
  {
    "input": "21*88+35=",
    "target": 1883
  },
  {
    "input": "64*27+21=",
    "target": 1749
  },
  {
    "input": "90*62+46=",
    "target": 5626
  },
  {
    "input": "24*98+81=",
    "target": 2433
  },
  {
    "input": "33*67+88=",
    "target": 2299
  },
  {
    "input": "64*35+93=",
    "target": 2333
  },
  {
    "input": "55*28+70=",
    "target": 1610
  },
  {
    "input": "38*11+97=",
    "target": 515
  },
  {
    "input": "50*66+87=",
    "target": 3387
  },
  {
    "input": "74*72+67=",
    "target": 5395
  },
  {
    "input": "9*81+92=",
    "target": 821
  },
  {
    "input": "76*96+82=",
    "target": 7378
  },
  {
    "input": "55*88+33=",
    "target": 4873
  },
  {
    "input": "85*2+72=",
    "target": 242
  },
  {
    "input": "84*77+85=",
    "target": 6553
  },
  {
    "input": "38*58+33=",
    "target": 2237
  },
  {
    "input": "98*9+42=",
    "target": 924
  },
  {
    "input": "94*30+8=",
    "target": 2828
  },
  {
    "input": "53*19+17=",
    "target": 1024
  },
  {
    "input": "61*29+12=",
    "target": 1781
  },
  {
    "input": "87*64+8=",
    "target": 5576
  },
  {
    "input": "96*51+8=",
    "target": 4904
  },
  {
    "input": "100*23+75=",
    "target": 2375
  },
  {
    "input": "71*54+41=",
    "target": 3875
  },
  {
    "input": "29*17+20=",
    "target": 513
  },
  {
    "input": "56*44+23=",
    "target": 2487
  },
  {
    "input": "16*1+94=",
    "target": 110
  },
  {
    "input": "43*48+43=",
    "target": 2107
  },
  {
    "input": "84*62+47=",
    "target": 5255
  },
  {
    "input": "34*65+37=",
    "target": 2247
  },
  {
    "input": "38*96+18=",
    "target": 3666
  },
  {
    "input": "36*8+25=",
    "target": 313
  },
  {
    "input": "52*86+83=",
    "target": 4555
  },
  {
    "input": "30*41+63=",
    "target": 1293
  },
  {
    "input": "7*27+11=",
    "target": 200
  },
  {
    "input": "31*61+70=",
    "target": 1961
  },
  {
    "input": "18*38+82=",
    "target": 766
  },
  {
    "input": "23*85+58=",
    "target": 2013
  },
  {
    "input": "28*9+92=",
    "target": 344
  },
  {
    "input": "73*96+22=",
    "target": 7030
  },
  {
    "input": "83*15+40=",
    "target": 1285
  },
  {
    "input": "30*1+98=",
    "target": 128
  },
  {
    "input": "6*79+6=",
    "target": 480
  },
  {
    "input": "28*4+67=",
    "target": 179
  },
  {
    "input": "22*74+50=",
    "target": 1678
  },
  {
    "input": "4*42+2=",
    "target": 170
  },
  {
    "input": "28*55+15=",
    "target": 1555
  },
  {
    "input": "63*54+74=",
    "target": 3476
  },
  {
    "input": "53*32+17=",
    "target": 1713
  },
  {
    "input": "79*35+48=",
    "target": 2813
  },
  {
    "input": "78*92+27=",
    "target": 7203
  },
  {
    "input": "78*93+84=",
    "target": 7338
  },
  {
    "input": "66*21+69=",
    "target": 1455
  },
  {
    "input": "25*25+41=",
    "target": 666
  },
  {
    "input": "49*20+27=",
    "target": 1007
  },
  {
    "input": "16*61+25=",
    "target": 1001
  },
  {
    "input": "3*2+68=",
    "target": 74
  },
  {
    "input": "2*95+50=",
    "target": 240
  },
  {
    "input": "100*19+43=",
    "target": 1943
  },
  {
    "input": "42*85+52=",
    "target": 3622
  },
  {
    "input": "58*49+11=",
    "target": 2853
  },
  {
    "input": "99*86+13=",
    "target": 8527
  },
  {
    "input": "16*97+86=",
    "target": 1638
  },
  {
    "input": "39*31+63=",
    "target": 1272
  },
  {
    "input": "57*3+99=",
    "target": 270
  },
  {
    "input": "25*83+93=",
    "target": 2168
  },
  {
    "input": "69*80+22=",
    "target": 5542
  },
  {
    "input": "75*58+67=",
    "target": 4417
  },
  {
    "input": "70*100+42=",
    "target": 7042
  },
  {
    "input": "44*33+44=",
    "target": 1496
  },
  {
    "input": "25*65+14=",
    "target": 1639
  },
  {
    "input": "99*8+15=",
    "target": 807
  },
  {
    "input": "3*4+99=",
    "target": 111
  },
  {
    "input": "53*69+70=",
    "target": 3727
  },
  {
    "input": "58*29+81=",
    "target": 1763
  },
  {
    "input": "71*21+29=",
    "target": 1520
  },
  {
    "input": "92*88+58=",
    "target": 8154
  },
  {
    "input": "31*24+82=",
    "target": 826
  },
  {
    "input": "70*98+1=",
    "target": 6861
  },
  {
    "input": "82*17+9=",
    "target": 1403
  },
  {
    "input": "39*8+100=",
    "target": 412
  },
  {
    "input": "91*52+19=",
    "target": 4751
  },
  {
    "input": "38*55+3=",
    "target": 2093
  },
  {
    "input": "54*69+90=",
    "target": 3816
  },
  {
    "input": "11*3+72=",
    "target": 105
  },
  {
    "input": "81*5+41=",
    "target": 446
  },
  {
    "input": "23*26+46=",
    "target": 644
  },
  {
    "input": "42*97+79=",
    "target": 4153
  },
  {
    "input": "63*13+44=",
    "target": 863
  },
  {
    "input": "64*67+85=",
    "target": 4373
  },
  {
    "input": "70*32+80=",
    "target": 2320
  },
  {
    "input": "18*27+86=",
    "target": 572
  },
  {
    "input": "70*95+36=",
    "target": 6686
  },
  {
    "input": "19*28+78=",
    "target": 610
  },
  {
    "input": "77*86+30=",
    "target": 6652
  },
  {
    "input": "43*78+98=",
    "target": 3452
  },
  {
    "input": "76*34+12=",
    "target": 2596
  },
  {
    "input": "76*32+18=",
    "target": 2450
  },
  {
    "input": "3*14+29=",
    "target": 71
  },
  {
    "input": "1*11+72=",
    "target": 83
  },
  {
    "input": "33*6+1=",
    "target": 199
  },
  {
    "input": "61*60+40=",
    "target": 3700
  },
  {
    "input": "93*83+13=",
    "target": 7732
  },
  {
    "input": "45*5+1=",
    "target": 226
  },
  {
    "input": "95*37+85=",
    "target": 3600
  },
  {
    "input": "58*96+44=",
    "target": 5612
  },
  {
    "input": "10*66+86=",
    "target": 746
  },
  {
    "input": "95*9+89=",
    "target": 944
  },
  {
    "input": "51*72+90=",
    "target": 3762
  },
  {
    "input": "24*74+35=",
    "target": 1811
  },
  {
    "input": "88*43+34=",
    "target": 3818
  },
  {
    "input": "70*39+40=",
    "target": 2770
  },
  {
    "input": "48*28+46=",
    "target": 1390
  },
  {
    "input": "27*39+15=",
    "target": 1068
  },
  {
    "input": "1*100+34=",
    "target": 134
  },
  {
    "input": "94*10+74=",
    "target": 1014
  },
  {
    "input": "2*18+41=",
    "target": 77
  },
  {
    "input": "66*90+9=",
    "target": 5949
  },
  {
    "input": "87*46+41=",
    "target": 4043
  },
  {
    "input": "86*53+92=",
    "target": 4650
  },
  {
    "input": "68*52+10=",
    "target": 3546
  },
  {
    "input": "71*19+58=",
    "target": 1407
  },
  {
    "input": "55*86+5=",
    "target": 4735
  },
  {
    "input": "17*70+37=",
    "target": 1227
  },
  {
    "input": "82*86+65=",
    "target": 7117
  },
  {
    "input": "63*79+11=",
    "target": 4988
  },
  {
    "input": "47*34+97=",
    "target": 1695
  },
  {
    "input": "54*82+82=",
    "target": 4510
  },
  {
    "input": "42*10+20=",
    "target": 440
  },
  {
    "input": "19*21+97=",
    "target": 496
  },
  {
    "input": "18*22+62=",
    "target": 458
  },
  {
    "input": "45*13+41=",
    "target": 626
  },
  {
    "input": "54*61+67=",
    "target": 3361
  },
  {
    "input": "28*53+50=",
    "target": 1534
  },
  {
    "input": "60*3+91=",
    "target": 271
  },
  {
    "input": "54*1+26=",
    "target": 80
  },
  {
    "input": "53*82+45=",
    "target": 4391
  },
  {
    "input": "45*61+55=",
    "target": 2800
  },
  {
    "input": "95*61+13=",
    "target": 5808
  },
  {
    "input": "94*47+67=",
    "target": 4485
  },
  {
    "input": "77*63+65=",
    "target": 4916
  },
  {
    "input": "81*50+81=",
    "target": 4131
  },
  {
    "input": "20*13+46=",
    "target": 306
  },
  {
    "input": "91*16+59=",
    "target": 1515
  },
  {
    "input": "18*89+29=",
    "target": 1631
  },
  {
    "input": "82*92+5=",
    "target": 7549
  },
  {
    "input": "84*60+37=",
    "target": 5077
  },
  {
    "input": "23*79+7=",
    "target": 1824
  },
  {
    "input": "16*10+70=",
    "target": 230
  },
  {
    "input": "75*18+62=",
    "target": 1412
  },
  {
    "input": "53*11+94=",
    "target": 677
  },
  {
    "input": "8*63+57=",
    "target": 561
  },
  {
    "input": "74*41+21=",
    "target": 3055
  },
  {
    "input": "57*98+74=",
    "target": 5660
  },
  {
    "input": "27*22+98=",
    "target": 692
  },
  {
    "input": "75*88+94=",
    "target": 6694
  },
  {
    "input": "43*40+93=",
    "target": 1813
  },
  {
    "input": "21*14+87=",
    "target": 381
  },
  {
    "input": "85*24+28=",
    "target": 2068
  },
  {
    "input": "100*72+84=",
    "target": 7284
  },
  {
    "input": "1*15+98=",
    "target": 113
  },
  {
    "input": "19*27+92=",
    "target": 605
  },
  {
    "input": "1*75+18=",
    "target": 93
  },
  {
    "input": "8*84+49=",
    "target": 721
  },
  {
    "input": "88*7+64=",
    "target": 680
  },
  {
    "input": "63*100+42=",
    "target": 6342
  },
  {
    "input": "58*85+80=",
    "target": 5010
  },
  {
    "input": "13*88+77=",
    "target": 1221
  },
  {
    "input": "88*95+42=",
    "target": 8402
  },
  {
    "input": "51*55+90=",
    "target": 2895
  },
  {
    "input": "18*26+38=",
    "target": 506
  },
  {
    "input": "98*10+69=",
    "target": 1049
  },
  {
    "input": "40*38+80=",
    "target": 1600
  },
  {
    "input": "19*29+45=",
    "target": 596
  },
  {
    "input": "73*82+1=",
    "target": 5987
  },
  {
    "input": "87*5+3=",
    "target": 438
  },
  {
    "input": "43*84+66=",
    "target": 3678
  },
  {
    "input": "25*30+79=",
    "target": 829
  },
  {
    "input": "19*66+75=",
    "target": 1329
  },
  {
    "input": "94*6+26=",
    "target": 590
  },
  {
    "input": "53*81+99=",
    "target": 4392
  },
  {
    "input": "58*10+94=",
    "target": 674
  },
  {
    "input": "91*8+95=",
    "target": 823
  },
  {
    "input": "22*41+61=",
    "target": 963
  },
  {
    "input": "59*28+56=",
    "target": 1708
  },
  {
    "input": "79*81+92=",
    "target": 6491
  },
  {
    "input": "11*76+36=",
    "target": 872
  },
  {
    "input": "76*23+79=",
    "target": 1827
  },
  {
    "input": "42*82+74=",
    "target": 3518
  },
  {
    "input": "13*81+15=",
    "target": 1068
  },
  {
    "input": "18*49+85=",
    "target": 967
  },
  {
    "input": "37*33+30=",
    "target": 1251
  },
  {
    "input": "53*22+16=",
    "target": 1182
  },
  {
    "input": "78*52+100=",
    "target": 4156
  },
  {
    "input": "42*12+13=",
    "target": 517
  },
  {
    "input": "64*77+35=",
    "target": 4963
  },
  {
    "input": "99*48+39=",
    "target": 4791
  },
  {
    "input": "41*10+18=",
    "target": 428
  },
  {
    "input": "94*25+71=",
    "target": 2421
  },
  {
    "input": "27*15+29=",
    "target": 434
  },
  {
    "input": "63*55+17=",
    "target": 3482
  },
  {
    "input": "60*79+25=",
    "target": 4765
  },
  {
    "input": "65*68+14=",
    "target": 4434
  },
  {
    "input": "28*72+34=",
    "target": 2050
  },
  {
    "input": "34*44+97=",
    "target": 1593
  },
  {
    "input": "66*52+18=",
    "target": 3450
  },
  {
    "input": "16*60+80=",
    "target": 1040
  },
  {
    "input": "22*34+88=",
    "target": 836
  },
  {
    "input": "64*74+23=",
    "target": 4759
  },
  {
    "input": "11*42+9=",
    "target": 471
  },
  {
    "input": "38*40+72=",
    "target": 1592
  },
  {
    "input": "51*23+8=",
    "target": 1181
  },
  {
    "input": "82*40+62=",
    "target": 3342
  },
  {
    "input": "1*82+93=",
    "target": 175
  },
  {
    "input": "11*13+37=",
    "target": 180
  },
  {
    "input": "10*27+42=",
    "target": 312
  },
  {
    "input": "54*85+9=",
    "target": 4599
  },
  {
    "input": "40*79+86=",
    "target": 3246
  },
  {
    "input": "12*21+58=",
    "target": 310
  },
  {
    "input": "67*1+16=",
    "target": 83
  },
  {
    "input": "19*5+100=",
    "target": 195
  },
  {
    "input": "10*73+1=",
    "target": 731
  },
  {
    "input": "57*86+89=",
    "target": 4991
  },
  {
    "input": "41*31+41=",
    "target": 1312
  },
  {
    "input": "8*87+43=",
    "target": 739
  },
  {
    "input": "65*95+25=",
    "target": 6200
  },
  {
    "input": "14*79+49=",
    "target": 1155
  },
  {
    "input": "73*64+17=",
    "target": 4689
  },
  {
    "input": "82*53+41=",
    "target": 4387
  },
  {
    "input": "48*4+8=",
    "target": 200
  },
  {
    "input": "18*98+6=",
    "target": 1770
  },
  {
    "input": "85*88+56=",
    "target": 7536
  },
  {
    "input": "60*91+88=",
    "target": 5548
  },
  {
    "input": "80*1+50=",
    "target": 130
  },
  {
    "input": "29*13+76=",
    "target": 453
  },
  {
    "input": "97*25+57=",
    "target": 2482
  },
  {
    "input": "2*65+22=",
    "target": 152
  },
  {
    "input": "72*99+70=",
    "target": 7198
  },
  {
    "input": "75*1+25=",
    "target": 100
  },
  {
    "input": "48*34+61=",
    "target": 1693
  },
  {
    "input": "3*76+45=",
    "target": 273
  },
  {
    "input": "81*20+96=",
    "target": 1716
  },
  {
    "input": "4*4+15=",
    "target": 31
  },
  {
    "input": "30*20+49=",
    "target": 649
  },
  {
    "input": "59*16+89=",
    "target": 1033
  },
  {
    "input": "58*86+74=",
    "target": 5062
  },
  {
    "input": "98*73+11=",
    "target": 7165
  },
  {
    "input": "1*74+6=",
    "target": 80
  },
  {
    "input": "81*31+68=",
    "target": 2579
  },
  {
    "input": "16*17+37=",
    "target": 309
  },
  {
    "input": "48*48+24=",
    "target": 2328
  },
  {
    "input": "21*79+62=",
    "target": 1721
  },
  {
    "input": "45*71+57=",
    "target": 3252
  },
  {
    "input": "98*100+60=",
    "target": 9860
  },
  {
    "input": "95*64+46=",
    "target": 6126
  },
  {
    "input": "57*3+28=",
    "target": 199
  },
  {
    "input": "73*86+24=",
    "target": 6302
  },
  {
    "input": "78*1+53=",
    "target": 131
  },
  {
    "input": "48*9+23=",
    "target": 455
  },
  {
    "input": "69*50+50=",
    "target": 3500
  },
  {
    "input": "89*21+19=",
    "target": 1888
  },
  {
    "input": "26*54+15=",
    "target": 1419
  },
  {
    "input": "54*9+49=",
    "target": 535
  },
  {
    "input": "49*98+99=",
    "target": 4901
  },
  {
    "input": "24*32+59=",
    "target": 827
  },
  {
    "input": "98*10+75=",
    "target": 1055
  },
  {
    "input": "89*59+92=",
    "target": 5343
  },
  {
    "input": "75*10+31=",
    "target": 781
  },
  {
    "input": "51*11+81=",
    "target": 642
  },
  {
    "input": "6*30+43=",
    "target": 223
  },
  {
    "input": "30*95+32=",
    "target": 2882
  },
  {
    "input": "83*78+64=",
    "target": 6538
  },
  {
    "input": "84*54+4=",
    "target": 4540
  },
  {
    "input": "36*33+39=",
    "target": 1227
  },
  {
    "input": "16*75+49=",
    "target": 1249
  },
  {
    "input": "52*79+78=",
    "target": 4186
  },
  {
    "input": "29*86+4=",
    "target": 2498
  },
  {
    "input": "60*73+87=",
    "target": 4467
  },
  {
    "input": "64*19+47=",
    "target": 1263
  },
  {
    "input": "53*3+1=",
    "target": 160
  },
  {
    "input": "41*44+28=",
    "target": 1832
  },
  {
    "input": "16*68+81=",
    "target": 1169
  },
  {
    "input": "67*53+8=",
    "target": 3559
  },
  {
    "input": "7*97+81=",
    "target": 760
  },
  {
    "input": "43*40+91=",
    "target": 1811
  },
  {
    "input": "72*88+36=",
    "target": 6372
  },
  {
    "input": "48*28+60=",
    "target": 1404
  },
  {
    "input": "51*54+5=",
    "target": 2759
  },
  {
    "input": "51*15+14=",
    "target": 779
  },
  {
    "input": "51*3+78=",
    "target": 231
  },
  {
    "input": "11*88+19=",
    "target": 987
  },
  {
    "input": "19*75+43=",
    "target": 1468
  },
  {
    "input": "86*64+98=",
    "target": 5602
  },
  {
    "input": "62*36+74=",
    "target": 2306
  },
  {
    "input": "84*3+22=",
    "target": 274
  },
  {
    "input": "74*83+31=",
    "target": 6173
  },
  {
    "input": "82*14+51=",
    "target": 1199
  },
  {
    "input": "74*99+1=",
    "target": 7327
  },
  {
    "input": "16*51+6=",
    "target": 822
  },
  {
    "input": "68*64+9=",
    "target": 4361
  },
  {
    "input": "81*83+85=",
    "target": 6808
  },
  {
    "input": "10*18+60=",
    "target": 240
  },
  {
    "input": "48*60+48=",
    "target": 2928
  },
  {
    "input": "89*69+26=",
    "target": 6167
  },
  {
    "input": "23*30+97=",
    "target": 787
  },
  {
    "input": "76*10+25=",
    "target": 785
  },
  {
    "input": "21*82+99=",
    "target": 1821
  },
  {
    "input": "79*83+28=",
    "target": 6585
  },
  {
    "input": "86*9+15=",
    "target": 789
  },
  {
    "input": "4*42+99=",
    "target": 267
  },
  {
    "input": "76*42+25=",
    "target": 3217
  },
  {
    "input": "40*49+99=",
    "target": 2059
  },
  {
    "input": "28*92+74=",
    "target": 2650
  },
  {
    "input": "42*65+94=",
    "target": 2824
  },
  {
    "input": "1*70+86=",
    "target": 156
  },
  {
    "input": "47*91+13=",
    "target": 4290
  },
  {
    "input": "44*98+77=",
    "target": 4389
  },
  {
    "input": "7*40+8=",
    "target": 288
  },
  {
    "input": "43*13+68=",
    "target": 627
  },
  {
    "input": "79*55+2=",
    "target": 4347
  },
  {
    "input": "92*66+55=",
    "target": 6127
  },
  {
    "input": "6*97+57=",
    "target": 639
  },
  {
    "input": "42*97+30=",
    "target": 4104
  },
  {
    "input": "38*49+7=",
    "target": 1869
  },
  {
    "input": "72*29+18=",
    "target": 2106
  },
  {
    "input": "65*18+27=",
    "target": 1197
  },
  {
    "input": "17*41+81=",
    "target": 778
  },
  {
    "input": "41*50+15=",
    "target": 2065
  },
  {
    "input": "4*12+61=",
    "target": 109
  },
  {
    "input": "62*9+41=",
    "target": 599
  },
  {
    "input": "53*83+95=",
    "target": 4494
  },
  {
    "input": "27*42+5=",
    "target": 1139
  },
  {
    "input": "25*57+4=",
    "target": 1429
  },
  {
    "input": "83*14+90=",
    "target": 1252
  },
  {
    "input": "42*3+59=",
    "target": 185
  },
  {
    "input": "22*90+3=",
    "target": 1983
  },
  {
    "input": "86*16+1=",
    "target": 1377
  },
  {
    "input": "96*97+59=",
    "target": 9371
  },
  {
    "input": "66*57+19=",
    "target": 3781
  },
  {
    "input": "10*90+49=",
    "target": 949
  },
  {
    "input": "94*49+35=",
    "target": 4641
  },
  {
    "input": "59*72+39=",
    "target": 4287
  },
  {
    "input": "50*62+73=",
    "target": 3173
  },
  {
    "input": "79*35+41=",
    "target": 2806
  },
  {
    "input": "56*73+100=",
    "target": 4188
  },
  {
    "input": "5*64+88=",
    "target": 408
  },
  {
    "input": "64*99+16=",
    "target": 6352
  },
  {
    "input": "56*12+20=",
    "target": 692
  },
  {
    "input": "38*80+60=",
    "target": 3100
  },
  {
    "input": "18*29+17=",
    "target": 539
  },
  {
    "input": "14*43+20=",
    "target": 622
  },
  {
    "input": "15*83+36=",
    "target": 1281
  },
  {
    "input": "87*8+88=",
    "target": 784
  },
  {
    "input": "14*16+73=",
    "target": 297
  },
  {
    "input": "4*16+65=",
    "target": 129
  },
  {
    "input": "17*18+68=",
    "target": 374
  },
  {
    "input": "50*39+85=",
    "target": 2035
  },
  {
    "input": "13*36+91=",
    "target": 559
  },
  {
    "input": "57*57+35=",
    "target": 3284
  },
  {
    "input": "44*14+17=",
    "target": 633
  },
  {
    "input": "100*10+56=",
    "target": 1056
  },
  {
    "input": "50*69+89=",
    "target": 3539
  },
  {
    "input": "8*65+96=",
    "target": 616
  },
  {
    "input": "19*85+40=",
    "target": 1655
  },
  {
    "input": "76*99+85=",
    "target": 7609
  },
  {
    "input": "75*71+6=",
    "target": 5331
  },
  {
    "input": "77*52+3=",
    "target": 4007
  },
  {
    "input": "5*21+56=",
    "target": 161
  },
  {
    "input": "100*61+75=",
    "target": 6175
  },
  {
    "input": "81*52+67=",
    "target": 4279
  },
  {
    "input": "73*59+89=",
    "target": 4396
  },
  {
    "input": "67*96+71=",
    "target": 6503
  },
  {
    "input": "91*7+15=",
    "target": 652
  },
  {
    "input": "81*80+100=",
    "target": 6580
  },
  {
    "input": "73*57+36=",
    "target": 4197
  },
  {
    "input": "81*36+38=",
    "target": 2954
  },
  {
    "input": "2*75+35=",
    "target": 185
  },
  {
    "input": "74*8+55=",
    "target": 647
  },
  {
    "input": "51*35+80=",
    "target": 1865
  },
  {
    "input": "75*46+22=",
    "target": 3472
  },
  {
    "input": "21*79+19=",
    "target": 1678
  },
  {
    "input": "92*42+30=",
    "target": 3894
  },
  {
    "input": "43*34+1=",
    "target": 1463
  },
  {
    "input": "87*59+68=",
    "target": 5201
  },
  {
    "input": "35*66+70=",
    "target": 2380
  },
  {
    "input": "69*59+22=",
    "target": 4093
  },
  {
    "input": "31*67+20=",
    "target": 2097
  },
  {
    "input": "83*68+39=",
    "target": 5683
  },
  {
    "input": "94*90+98=",
    "target": 8558
  },
  {
    "input": "78*74+75=",
    "target": 5847
  },
  {
    "input": "1*6+23=",
    "target": 29
  },
  {
    "input": "41*19+73=",
    "target": 852
  },
  {
    "input": "59*93+9=",
    "target": 5496
  },
  {
    "input": "50*40+42=",
    "target": 2042
  }
]